BsSalary_Extractor/__init__.py
BsSalary_Extractor/constants.py
BsSalary_Extractor/data_extractor.py
BsSalary_Extractor/data_extractor2.py
BsSalary_Extractor/data_extractor_only_sc.py
BsSalary_Extractor/data_extractor_revibe.py
BsSalary_Extractor/functions.py
BsSalary_Extractor-1.3.9.dist-info/LICENSE
BsSalary_Extractor-1.3.9.dist-info/METADATA
BsSalary_Extractor-1.3.9.dist-info/WHEEL
BsSalary_Extractor-1.3.9.dist-info/top_level.txt
BsSalary_Extractor-1.3.9.dist-info/RECORD
