Metadata-Version: 2.1
Name: BsSalary_Extractor
Version: 1.3.9
Summary: This repository contains a Python program designed to execute Optical Character Recognition (OCR) and Facial Recognition on images.
Home-page: 
Author: Fahad Patel
Author-email: fahadpatel1403@gmail.com
Classifier: Programming Language :: Python :: 3
Classifier: License :: OSI Approved :: MIT License
Classifier: Operating System :: OS Independent
Requires-Python: >=3.7
License-File: LICENSE
Requires-Dist: aiohttp ==3.9.3
Requires-Dist: aiosignal ==1.3.1
Requires-Dist: arabic-reshaper ==3.0.0
Requires-Dist: async-timeout ==4.0.3
Requires-Dist: attrs ==23.2.0
Requires-Dist: build ==1.0.3
Requires-Dist: cachetools ==5.3.2
Requires-Dist: certifi ==2024.2.2
Requires-Dist: chardet ==3.0.4
Requires-Dist: charset-normalizer ==3.3.2
Requires-Dist: docutils ==0.20.1
Requires-Dist: frozenlist ==1.4.1
Requires-Dist: fuzzywuzzy ==0.18.0
Requires-Dist: google-api-core ==2.17.1
Requires-Dist: google-auth ==2.28.0
Requires-Dist: google-cloud-vision ==3.7.0
Requires-Dist: googleapis-common-protos ==1.62.0
Requires-Dist: googletrans ==4.0.0rc1
Requires-Dist: grpcio ==1.60.1
Requires-Dist: grpcio-status ==1.60.1
Requires-Dist: h11 ==0.9.0
Requires-Dist: h2 ==3.2.0
Requires-Dist: hijri-converter ==2.3.1
Requires-Dist: hpack ==3.0.0
Requires-Dist: hstspreload ==2024.4.1
Requires-Dist: httpcore ==0.9.1
Requires-Dist: httpx ==0.13.3
Requires-Dist: hyperframe ==5.2.0
Requires-Dist: idna ==2.10
Requires-Dist: importlib-metadata ==7.0.1
Requires-Dist: jaraco.classes ==3.3.1
Requires-Dist: keyring ==24.3.0
Requires-Dist: langdetect ==1.0.9
Requires-Dist: markdown-it-py ==3.0.0
Requires-Dist: mdurl ==0.1.2
Requires-Dist: more-itertools ==10.2.0
Requires-Dist: multidict ==6.0.5
Requires-Dist: nh3 ==0.2.15
Requires-Dist: numpy ==1.26.4
Requires-Dist: openai ==0.28.1
Requires-Dist: opencv-python ==4.9.0.80
Requires-Dist: packaging ==23.2
Requires-Dist: pandas ==2.2.2
Requires-Dist: pkginfo ==1.9.6
Requires-Dist: proto-plus ==1.23.0
Requires-Dist: protobuf ==4.25.3
Requires-Dist: pyasn1 ==0.5.1
Requires-Dist: pyasn1-modules ==0.3.0
Requires-Dist: Pygments ==2.17.2
Requires-Dist: PyMuPDF ==1.23.21
Requires-Dist: PyMuPDFb ==1.23.9
Requires-Dist: PyPDF2 ==3.0.1
Requires-Dist: pyproject-hooks ==1.0.0
Requires-Dist: python-dateutil ==2.9.0.post0
Requires-Dist: pytz ==2024.1
Requires-Dist: readme-renderer ==42.0
Requires-Dist: requests ==2.31.0
Requires-Dist: requests-toolbelt ==1.0.0
Requires-Dist: rfc3986 ==1.5.0
Requires-Dist: rich ==13.7.0
Requires-Dist: rsa ==4.9
Requires-Dist: six ==1.16.0
Requires-Dist: sniffio ==1.3.1
Requires-Dist: tomli ==2.0.1
Requires-Dist: tqdm ==4.66.2
Requires-Dist: twine ==5.0.0
Requires-Dist: typing-extensions ==4.11.0
Requires-Dist: tzdata ==2024.1
Requires-Dist: Unidecode ==1.3.8
Requires-Dist: urllib3 ==2.2.0
Requires-Dist: yarl ==1.9.4
Requires-Dist: zipp ==3.17.0
